browserlify/__init__.py
browserlify/command.py
browserlify/option.py
browserlify-1.0.4.data/scripts/browserlify
browserlify-1.0.4.dist-info/LICENSE
browserlify-1.0.4.dist-info/METADATA
browserlify-1.0.4.dist-info/WHEEL
browserlify-1.0.4.dist-info/top_level.txt
browserlify-1.0.4.dist-info/RECORD
