Metadata-Version: 2.1
Name: browserlify
Version: 1.0.4
Summary: PDF generation, Web Scraping with headless chrome from browserlify.com
Home-page: https://github.com/browserlify/python-sdk
Author: browserlify
Author-email: hello@browserlify.com
License: Apache Software License
Classifier: Development Status :: 5 - Production/Stable
Classifier: Programming Language :: Python :: 3 :: Only
Classifier: Intended Audience :: Developers
Classifier: Operating System :: OS Independent
Classifier: License :: OSI Approved :: Apache Software License
Classifier: Topic :: Software Development :: Libraries
Classifier: Topic :: Scientific/Engineering :: Image Processing
Classifier: Topic :: Internet :: WWW/HTTP :: Browsers
Requires: requests
License-File: LICENSE
